hypergrid/__init__.py
hypergrid/dimension.py
hypergrid/dsl.py
hypergrid/grid.py
hypergrid/py.typed
hypergrid/util.py
hypergrid/ext/__init__.py
hypergrid/ext/sklearn.py
hypergrid/gen/__init__.py
hypergrid/gen/distribution.py
hypergrid/gen/iterable.py
hypergrid-0.0.1.dist-info/LICENSE
hypergrid-0.0.1.dist-info/METADATA
hypergrid-0.0.1.dist-info/WHEEL
hypergrid-0.0.1.dist-info/top_level.txt
hypergrid-0.0.1.dist-info/RECORD
