Metadata-Version: 2.1
Name: hypergrid
Version: 0.0.1
Summary: Hypergrid enables concise declaration of parameter grids for hyperparameter optimization and batch jobs.
Author-email: Justin Yan <justin@iomorphic.com>
Project-URL: Homepage, https://github.com/justin-yan/hypergrid
Classifier: Development Status :: 4 - Beta
Classifier: Intended Audience :: Developers
Classifier: Operating System :: OS Independent
Classifier: License :: OSI Approved :: MIT License
Classifier: Programming Language :: Python
Classifier: Programming Language :: Python :: 3
Classifier: Programming Language :: Python :: 3.11
Classifier: Programming Language :: Python :: 3.12
Classifier: Programming Language :: Python :: 3.13
Requires-Python: >=3.11
License-File: LICENSE
Provides-Extra: sklearn
Requires-Dist: scikit-learn<2; extra == "sklearn"
